selfneuron/Logger.py
selfneuron/__init__.py
selfneuron/client.py
selfneuron/custom_exception.py
selfneuron/test.py
tests/__init__.py
tests/test_basic_connection.py
selfneuron-1.0.8.dist-info/METADATA
selfneuron-1.0.8.dist-info/WHEEL
selfneuron-1.0.8.dist-info/top_level.txt
selfneuron-1.0.8.dist-info/RECORD
