Metadata-Version: 2.1
Name: selfneuron
Version: 1.0.8
Summary: An SDK for interacting with SelfNeuron using Python
Home-page: https://github.com/ipowersoft/snn-client-sdks
Author: iPowersoft/SelfNeuron
Author-email: raman@ipowersoft.com
Requires-Dist: requests
Requires-Dist: loguru
